console_creator/__init__.py
console_creator/__main__.py
console_creator/console_creator.py
console_creator/main.py
python_console_creator-1.2.0.dist-info/LICENSE
python_console_creator-1.2.0.dist-info/METADATA
python_console_creator-1.2.0.dist-info/WHEEL
python_console_creator-1.2.0.dist-info/top_level.txt
python_console_creator-1.2.0.dist-info/RECORD
